async_tba-0.0.1.dist-info/METADATA
async_tba-0.0.1.dist-info/RECORD
async_tba-0.0.1.dist-info/WHEEL
async_tba-0.0.1.dist-info/top_level.txt
bluealliance/__init__.py
bluealliance/alliance.py
bluealliance/client.py
bluealliance/conn_state.py
bluealliance/constants.py
bluealliance/event.py
bluealliance/mini_models.py
bluealliance/model.py
bluealliance/team.py
