Metadata-Version: 2.1
Name: async-tba
Version: 0.0.1
Summary: aiohttp based Python API for The Blue Alliance
Home-page: https://github.com/c-x-berger/async_tba
Author: Caleb Xavier Berger
Author-email: caleb.x.berger@gmail.com
License: UNKNOWN
Platform: UNKNOWN
Classifier: Programming Language :: Python :: 3
Classifier: License :: OSI Approved :: MIT License
Classifier: Operating System :: OS Independent
